{"api-examples.md":"DUpPHIeh","builds_companion.md":"CHadzGqQ","builds_khoraorigin.md":"-JMxIavZ","builds_khorasteelpath.md":"Bf-A6Fly","builds_nekrosossp.md":"DXZMMDrx","builds_novaossp.md":"Cgyw4-CU","builds_operator.md":"DF7aRIwb","builds_weapons.md":"C_Av82LQ","credits.md":"BDPB-0uO","farming_ferrite.md":"_BlPnH3Y","farming_nanospore.md":"cOLku5k3","farming_polymerbundle.md":"DBOGbgLX","get-started_missionconditions.md":"DtV-oj7J","get-started_why.md":"8rIWbEVm","index.md":"DNVNSitI","log.md":"COE_-Psu","markdown-examples.md":"kiO4PbS3","welcome.md":"DpzWcLVs"}
